cohere/__init__.py
cohere/best_choices.py
cohere/client.py
cohere/embeddings.py
cohere/error.py
cohere/generation.py
cohere/response.py
cohere/tokenize.py
cohere/tokens.py
cohere/tokenizer/__init__.py
cohere/tokenizer/build.py
cohere/tokenizer/go.py
cohere/tokenizer/tokenizer.py
testpythonalex-1.0.4.dist-info/LICENSE
testpythonalex-1.0.4.dist-info/METADATA
testpythonalex-1.0.4.dist-info/WHEEL
testpythonalex-1.0.4.dist-info/top_level.txt
testpythonalex-1.0.4.dist-info/RECORD
