Metadata-Version: 2.1
Name: testpythonalex
Version: 1.0.4
Summary: Test Python Library
Home-page: https://github.com/alexguo247/cohere-python
Author: alexguo247
Author-email: alexguo247@gmail.com
License: UNKNOWN
Platform: UNKNOWN
Classifier: Programming Language :: Python :: 3
Classifier: License :: OSI Approved :: MIT License
Classifier: Operating System :: OS Independent
Requires-Python: >=3.6
License-File: LICENSE
Requires-Dist: requests
